setup.py
radix_repr_var/__init__.py
radix_repr_var/binary.py
radix_repr_var/octal.py
radix_repr_var/radix.py
radix_repr_var.egg-info/PKG-INFO
radix_repr_var.egg-info/SOURCES.txt
radix_repr_var.egg-info/dependency_links.txt
radix_repr_var.egg-info/not-zip-safe
radix_repr_var.egg-info/top_level.txt