Metadata-Version: 1.0
Name: radix-repr-var
Version: 0.1
Summary: Radix Representations Variations
Home-page: UNKNOWN
Author: Alfonso Ridolfo
Author-email: alfonso.ridolfo@gmail.com
License: UNKNOWN
Platform: UNKNOWN
